typegraph/__init__.py
typegraph/converter/__init__.py
typegraph/converter/base.py
typegraph/type_utils.py
typegraph3-0.3.2.dist-info/METADATA
typegraph3-0.3.2.dist-info/WHEEL
typegraph3-0.3.2.dist-info/entry_points.txt
typegraph3-0.3.2.dist-info/licenses/LICENSE
typegraph3-0.3.2.dist-info/RECORD
