Metadata-Version: 2.1
Name: typegraph3
Version: 0.3.2
Summary: 基于graph的类型转换工具
Author-Email: luxuncang <luxuncang@qq.com>
License: MIT
Requires-Python: >=3.10
Requires-Dist: networkx>=3.3
Requires-Dist: typing-tool>=0.1.0
